MANIFEST.in
RELEASE-VERSION
pavement.py
paver-minilib.zip
setup.py
version.py
avr_helpers/__init__.py
avr_helpers.egg-info/PKG-INFO
avr_helpers.egg-info/SOURCES.txt
avr_helpers.egg-info/dependency_links.txt
avr_helpers.egg-info/requires.txt
avr_helpers.egg-info/top_level.txt