Metadata-Version: 1.0
Name: avr-helpers
Version: 0.1
Summary: Minimal tool-set for flashing bit-streams to AVR micro-controllers.
Home-page: http://github.com/wheeler-microfluidics/avr_helpers.git
Author: Christian Fobel
Author-email: christian@fobel.net
License: GPLv2
Platform: UNKNOWN
